.coveragerc
.travis.yml
AUTHORS.rst
CHANGES.rst
LICENSE.txt
README.rst
requirements.txt
setup.cfg
setup.py
test-requirements.txt
docs/Makefile
docs/authors.rst
docs/changes.rst
docs/conf.py
docs/index.rst
docs/license.rst
docs/_static/.gitignore
farneback3d/A.A+A.b.wxmx
farneback3d/__init__.py
farneback3d/_farneback3d.py
farneback3d/_filtering.py
farneback3d/_utils.py
farneback3d/farneback_kernels.cu
farneback3d/filtering.cu
farneback3d/resize.cu
farneback3d.egg-info/PKG-INFO
farneback3d.egg-info/SOURCES.txt
farneback3d.egg-info/dependency_links.txt
farneback3d.egg-info/not-zip-safe
farneback3d.egg-info/requires.txt
farneback3d.egg-info/top_level.txt
tests/conftest.py
tests/test_synthetic_volumes.py
travis/install_cuda.sh