Metadata-Version: 2.1
Name: farneback3d
Version: 0.1.3
Summary: CUDA-accelerated volumetric optical flow estimation using the Farneback algorithm
Home-page: https://github.com/theHamsta
Author: Stephan Seitz
Author-email: stephan.seitz@yahoo.de
License: GPL v3
Platform: UNKNOWN
Classifier: Development Status :: 4 - Beta
Classifier: Programming Language :: Python
Provides-Extra: test
